xls_report/__init__.py
xls_report-0.0.8.dist-info/METADATA
xls_report-0.0.8.dist-info/WHEEL
xls_report-0.0.8.dist-info/top_level.txt
xls_report-0.0.8.dist-info/RECORD
