Metadata-Version: 2.1
Name: xls-report
Version: 0.0.8
Summary: Database report generation in .xls format according to the xml description
Home-page: https://github.com/oleglpts/xls_report
Author: Oleg Lupats
Author-email: oleglupats@gmail.com
License: MIT
Platform: any
Classifier: Programming Language :: Python :: 3
Classifier: Programming Language :: Python :: 3.5
Requires-Python: >=3
Requires-Dist: lxml (>=4.3.4)
Requires-Dist: xlwt (>=1.3.0)
Requires-Dist: pycurl (>=7.43.0.3)
